touhou_ura/__init__.py
touhou_ura/exceptions.py
touhou_ura/main.html
touhou_ura/style4.css
touhou_ura/ura.py
touhou_ura-0.0.1.dist-info/LICENSE
touhou_ura-0.0.1.dist-info/METADATA
touhou_ura-0.0.1.dist-info/WHEEL
touhou_ura-0.0.1.dist-info/top_level.txt
touhou_ura-0.0.1.dist-info/RECORD
