Metadata-Version: 2.1
Name: touhou-ura
Version: 0.0.1
Summary: Python tool to get or/and download data from touhou-ura threads (futaba)
Home-page: https://github.com/blackrose514/touhou-ura
Author: blackrose514
Author-email: dmtri3sukuna@gmail.com
License: MIT
Download-URL: https://github.com/blackrose514/touhou-ura/releases
Keywords: touhou,futaba,4chan
Platform: UNKNOWN
Classifier: Programming Language :: Python :: 3
Classifier: Programming Language :: Python :: 3.6
Classifier: Programming Language :: Python :: 3.7
Classifier: License :: OSI Approved :: MIT License
Classifier: Operating System :: OS Independent
Requires-Dist: requests
Requires-Dist: tqdm
Requires-Dist: beautifulsoup4
